odoo10_addon_base_jsonify-10.0.1.1.0-nspkg.pth
odoo/addons/base_jsonify/README.rst
odoo/addons/base_jsonify/__init__.py
odoo/addons/base_jsonify/__manifest__.py
odoo/addons/base_jsonify/demo/export_demo.xml
odoo/addons/base_jsonify/demo/ir.exports.line.csv
odoo/addons/base_jsonify/i18n/base_jsonify.pot
odoo/addons/base_jsonify/models/__init__.py
odoo/addons/base_jsonify/models/ir_export.py
odoo/addons/base_jsonify/models/ir_exports_line.py
odoo/addons/base_jsonify/models/models.py
odoo/addons/base_jsonify/readme/CONTRIBUTORS.rst
odoo/addons/base_jsonify/readme/DESCRIPTION.rst
odoo/addons/base_jsonify/static/description/icon.png
odoo/addons/base_jsonify/static/description/index.html
odoo/addons/base_jsonify/tests/__init__.py
odoo/addons/base_jsonify/tests/test_get_parser.py
odoo/addons/base_jsonify/tests/test_ir_exports_line.py
odoo/addons/base_jsonify/views/ir_exports_view.xml
odoo10_addon_base_jsonify-10.0.1.1.0.dist-info/METADATA
odoo10_addon_base_jsonify-10.0.1.1.0.dist-info/WHEEL
odoo10_addon_base_jsonify-10.0.1.1.0.dist-info/namespace_packages.txt
odoo10_addon_base_jsonify-10.0.1.1.0.dist-info/top_level.txt
odoo10_addon_base_jsonify-10.0.1.1.0.dist-info/RECORD
